<plugin>
<name>30701</name>
<link>plugin://plugin.video.musashi/?action=openSettings</link>
<thumbnail></thumbnail>
</plugin>



<dir>
<title>Lilly's TV Shows</title>
<trakt>https://trakt.tv/users/ronald.lukasik/lists/lilly</trakt>
</dir>

<dir>
<title>Beth's TV Shows</title>
<trakt>https://api.trakt.tv/users/ronald.lukasik/lists/beth/items</trakt>
</dir>

<dir>
<title>Ron's TV Shows</title>
<trakt>https://api.trakt.tv/users/ronald.lukasik/lists/ron/items</trakt>
</dir>

<dir>
<title>tv lists</title>
<trakt><dir>
<title></title>
<trakt>https://api.trakt.tv/users/ronald.lukasik/lists/</trakt>
</dir></trakt>
</dir>